simplex/__init__.py
simplex/geometry.py
simplex/materials.py
simplex/beam/__init__.py
simplex/beam/cli/__init__.py
simplex/beam/cli/commands.py
simplex/column/__init__.py
simplex/core/actions/IO.py
simplex/core/actions/__init__.py
simplex/core/actions/analysis.py
simplex/core/actions/design.py
simplex/core/actions/fetch.py
simplex/core/auth/__init__.py
simplex/core/auth/device_flow.py
simplex/core/cli/__init__.py
simplex/core/cli/auth_commands.py
simplex/core/cli/main.py
simplex/core/config/__init__.py
simplex/core/config/auth.py
simplex/core/config/endpoints.py
simplex/core/config/environment.py
simplex/core/converters/design_settings.py
simplex/core/converters/foundation_converter.py
simplex/core/error/__init__.py
simplex/core/error/handling.py
simplex/core/geometry/__init__.py
simplex/core/geometry/line.py
simplex/core/geometry/point.py
simplex/core/materials/__init__.py
simplex/core/materials/materials.py
simplex/core/numbers/__init__.py
simplex/core/numbers/units.py
simplex/core/protos/generated/__init__.py
simplex/core/protos/generated/element_pb2.py
simplex/core/protos/generated/element_pb2.pyi
simplex/core/protos/generated/input_pb2.py
simplex/core/protos/generated/input_pb2.pyi
simplex/core/protos/generated/output_pb2.py
simplex/core/protos/generated/output_pb2.pyi
simplex/core/protos/generated/project_pb2.py
simplex/core/protos/generated/project_pb2.pyi
simplex/core/protos/generated/sections_pb2.py
simplex/core/protos/generated/sections_pb2.pyi
simplex/core/protos/generated/stage_pb2.py
simplex/core/protos/generated/stage_pb2.pyi
simplex/core/protos/generated/structure_pb2.py
simplex/core/protos/generated/structure_pb2.pyi
simplex/core/protos/generated/support_pb2.py
simplex/core/protos/generated/support_pb2.pyi
simplex/core/protos/generated/Design/__init__.py
simplex/core/protos/generated/Design/concrete_pb2.py
simplex/core/protos/generated/Design/concrete_pb2.pyi
simplex/core/protos/generated/Design/design_pb2.py
simplexpy-1.0.1.dist-info/METADATA
simplexpy-1.0.1.dist-info/WHEEL
simplexpy-1.0.1.dist-info/entry_points.txt
simplexpy-1.0.1.dist-info/top_level.txt
simplexpy-1.0.1.dist-info/RECORD
