Metadata-Version: 2.4
Name: simplexpy
Version: 1.0.1
Summary: A comprehensive toolbox for structural engineering calculations
Author-email: StruSoft <simplex.api@strusoft.com>
Maintainer-email: Marco Pellegrino <marco.pellegrino@strusoft.com>
Project-URL: Homepage, http://www.strusoft.com/
Project-URL: Documentation, https://simplex-docs.onstrusoft.com/simple
Project-URL: Issues, https://strusoft.freshdesk.com/en/support/tickets/new
Project-URL: Download, https://strusoft.com/
Keywords: structural-engineering,foundation-design,eurocode,civil-engineering,structural-analysis,concrete-design,geotechnical,construction
Classifier: Intended Audience :: Developers
Classifier: Intended Audience :: Science/Research
Classifier: License :: OSI Approved :: Apache Software License
Classifier: Programming Language :: Python :: 3
Classifier: Operating System :: Microsoft :: Windows
Classifier: Operating System :: MacOS
Classifier: Topic :: Scientific/Engineering
Requires-Python: >=3.12.10
Requires-Dist: protobuf==4.25.3
Requires-Dist: click>=8.1.7
Requires-Dist: openpyxl>=3.1.0
Requires-Dist: requests>=2.31.0
